{
  "filename": "Anhang_0_89f2ccb8-cd44-42d1-8543-62fb154f58a2.pdf",
  "extraction_method": "OCR_REQUIRED after PyMuPDF/pypdf/pdfplumber/OCR attempts",
  "password_success": "NO",
  "text_length": 0,
  "detected_insurance_name": "",
  "detected_dates": [],
  "detected_amounts": [],
  "status": "OCR_REQUIRED",
  "source_file": "00_INBOX - Входящи - Eingang/Accounting_Organized/04_Health_Insurance/Anhang_0_89f2ccb8-cd44-42d1-8543-62fb154f58a2.pdf",
  "technical_errors": [
    "PyMuPDF password authentication failed",
    "pypdf password decrypt failed",
    "pdfplumber failed: ",
    "PDF OCR password authentication failed"
  ]
}
